google_pronouncer/__init__.py
google_pronouncer/__main__.py
google_pronouncer/cli.py
google_pronouncer/downloader.py
google_pronouncer-0.3.0.dist-info/LICENSE
google_pronouncer-0.3.0.dist-info/METADATA
google_pronouncer-0.3.0.dist-info/WHEEL
google_pronouncer-0.3.0.dist-info/entry_points.txt
google_pronouncer-0.3.0.dist-info/top_level.txt
google_pronouncer-0.3.0.dist-info/RECORD
