Metadata-Version: 2.2
Name: google-pronouncer
Version: 0.3.0
Summary: A library for downloading pronunciation MP3 files from Google's dictionary service
Home-page: https://github.com/HachiroSan/google-pronouncer
Author: Hachiro
Author-email: farhad@farhad.my
Project-URL: Homepage, https://github.com/HachiroSan/google-pronouncer
Project-URL: Bug Tracker, https://github.com/HachiroSan/google-pronouncer/issues
Project-URL: Documentation, https://github.com/HachiroSan/google-pronouncer#readme
Keywords: pronunciation,audio,google,dictionary,text-to-speech,education,language
Classifier: Development Status :: 4 - Beta
Classifier: Intended Audience :: Developers
Classifier: Intended Audience :: Education
Classifier: License :: OSI Approved :: MIT License
Classifier: Operating System :: OS Independent
Classifier: Programming Language :: Python :: 3
Classifier: Programming Language :: Python :: 3.7
Classifier: Programming Language :: Python :: 3.8
Classifier: Programming Language :: Python :: 3.9
Classifier: Programming Language :: Python :: 3.10
Classifier: Programming Language :: Python :: 3.11
Classifier: Topic :: Education
Classifier: Topic :: Multimedia :: Sound/Audio
Classifier: Topic :: Software Development :: Libraries :: Python Modules
Requires-Python: >=3.7
License-File: LICENSE
Requires-Dist: requests<3.0.0,>=2.31.0
Requires-Dist: tqdm>=4.65.0
Dynamic: author
Dynamic: author-email
Dynamic: classifier
Dynamic: description
Dynamic: description-content-type
Dynamic: home-page
Dynamic: keywords
Dynamic: project-url
Dynamic: requires-dist
Dynamic: requires-python
Dynamic: summary
